utilitytools/__init__.py
utilitytools/run.py
utilitytools-0.0.8.dist-info/METADATA
utilitytools-0.0.8.dist-info/WHEEL
utilitytools-0.0.8.dist-info/top_level.txt
utilitytools-0.0.8.dist-info/RECORD
